lambda_ex/__init__.py
lambda_ex/grafting.py
lambda_ex/lambdex.py
lambda_ex/later.py
lambda_ex-1.1.0.dist-info/LICENSE
lambda_ex-1.1.0.dist-info/WHEEL
lambda_ex-1.1.0.dist-info/METADATA
lambda_ex-1.1.0.dist-info/RECORD
