Metadata-Version: 2.1
Name: lambda-ex
Version: 1.1.0
Summary: Python lambda expression in multiple lines.
Home-page: https://github.com/likianta/lambda-ex
License: MIT
Author: Likianta
Author-email: likianta@foxmail.com
Requires-Python: >=3.8,<4.0
Classifier: License :: OSI Approved :: MIT License
Classifier: Programming Language :: Python :: 3
Classifier: Programming Language :: Python :: 3.10
Classifier: Programming Language :: Python :: 3.8
Classifier: Programming Language :: Python :: 3.9
